vomit/__init__.py
vomit/__main__.py
vomit/py.typed
py_vomit-1.0.0.dist-info/METADATA
py_vomit-1.0.0.dist-info/WHEEL
py_vomit-1.0.0.dist-info/licenses/LICENSE
py_vomit-1.0.0.dist-info/RECORD
