Metadata-Version: 2.2
Name: py-vomit
Version: 1.0.0
Summary: Somewhat unintelligible
Project-URL: Repository, https://github.com/bhmt/vomit
Author: bhmt, torvalds
Maintainer: bhmt, torvalds
License: MIT License
Keywords: obfuscation,unicode,utf-8
Classifier: Intended Audience :: Developers
Classifier: License :: OSI Approved :: MIT License
Classifier: Operating System :: OS Independent
Classifier: Programming Language :: Python :: 3 :: Only
Classifier: Programming Language :: Python :: 3.10
Classifier: Programming Language :: Python :: 3.11
Classifier: Programming Language :: Python :: 3.12
Classifier: Topic :: Security
Classifier: Topic :: Software Development
Classifier: Topic :: Software Development :: Build Tools
Classifier: Topic :: Software Development :: Code Generators
Classifier: Typing :: Typed
Requires-Python: >=3.10
Provides-Extra: check
Requires-Dist: mypy>=1.3.0; extra == 'check'
Requires-Dist: ruff>=0.0.277; extra == 'check'
Requires-Dist: tox>=4.6.0; extra == 'check'
Provides-Extra: test
Requires-Dist: pytest-cov>=4.1.0; extra == 'test'
Requires-Dist: pytest>=7.3.1; extra == 'test'
